setup.py
mongodog/__init__.py
mongodog/reporters.py
mongodog/sniffer.py
mongodog/utils.py
mongodog.egg-info/PKG-INFO
mongodog.egg-info/SOURCES.txt
mongodog.egg-info/dependency_links.txt
mongodog.egg-info/not-zip-safe
mongodog.egg-info/top_level.txt