Metadata-Version: 1.1
Name: mongodog
Version: 0.1.1
Summary: 
